rectifiedgrid/__init__.py
rectifiedgrid/core.py
rectifiedgrid/core_v1.2.py
rectifiedgrid/demo.py
rectifiedgrid/hillshade.py
rectifiedgrid/sandbox.py
rectifiedgrid/utils.py
rectifiedgrid-3.1.0.dist-info/licenses/LICENSE.txt
rectifiedgrid-3.1.0.dist-info/METADATA
rectifiedgrid-3.1.0.dist-info/WHEEL
rectifiedgrid-3.1.0.dist-info/pbr.json
rectifiedgrid-3.1.0.dist-info/top_level.txt
rectifiedgrid-3.1.0.dist-info/RECORD
