Metadata-Version: 2.4
Name: rectifiedgrid
Version: 3.1.0
Summary: RectifiedGrid is a python module to deal with rectified grid.
Home-page: http://todo.todo
Author: Stefano Menegon
Author-email: ste.menegon@gmail.com
License: GPL3
Classifier: Development Status :: 5 - Production/Stable
Classifier: Topic :: Utilities
Classifier: License :: OSI Approved :: GNU General Public License v3 (GPLv3)
Requires-Python: >=3.8
License-File: LICENSE.txt
Requires-Dist: numpy
Requires-Dist: geopandas
Requires-Dist: scipy
Requires-Dist: rasterio
Requires-Dist: fiona
Requires-Dist: contextily
Requires-Dist: rioxarray
Requires-Dist: shapely
Requires-Dist: rtree
Requires-Dist: pandas
Requires-Dist: affine
Requires-Dist: matplotlib
Requires-Dist: mapclassify
Requires-Dist: gisdata
Requires-Dist: pyepsg
Dynamic: author
Dynamic: author-email
Dynamic: classifier
Dynamic: home-page
Dynamic: keywords
Dynamic: license
Dynamic: license-file
Dynamic: requires-dist
Dynamic: summary
